[
  {
      "id": "1",
      "nome": "Grey´s Anatomy",
      "foto": "https://i.pinimg.com/originals/33/39/9d/33399df9faacc5de9e3928f52fabbacf.jpg",
      "descricao": "Durante sua residência, Meredith Grey vive paixões profissionais e pessoais com seus colegas médicos em um hospital de Seattle.",
      "elenco": "Ellen Pompeo,Sandra Oh,Katherine Heigl"
  },
  {
      "id": "2",
      "nome": "Vingadores Guerra Infinita",
      "foto": "https://i.pinimg.com/736x/63/c7/41/63c741c433aa938eadafdbd386e4e676.jpg",
      "descricao": "Em Vingadores: Guerra Infinita, Thanos (Josh Brolin) enfim chega à Terra, disposto a reunir as Joias do Infinito. Para enfrentá-lo, os Vingadores precisam unir forças com os Guardiões da Galáxia, ao mesmo tempo em que lidam com desavenças entre alguns de seus integrantes.",
      "elenco": "Tom Holland,Chris Evans,Scarlett Johansson,Robert Downey Jr" 
  },
  {
      "id": "3",
      "nome": "Black Summer",
      "foto": "https://i.pinimg.com/736x/e6/5a/3a/e65a3a4a13f4c0533bc1a74dd38673fb.jpg",
      "descricao": "Nos primeiros dias de um sombrio apocalipse zumbi, estranhos se unem para sobreviver e voltar para aqueles que amam.",
      "elenco": "Jaime King,Justin Chu Cary,Christine Lee"  
  }
]